cdp_ts/__init__.py
cdp_ts/core/__init__.py
cdp_ts/core/cdp.py
cdp_ts/core/pso.py
cdp_ts/core/shapelet.py
cdp_ts/core/shapelet_classifier.py
cdp_ts/utils/__init__.py
cdp_ts/utils/btree.py
cdp_ts/utils/dataset.py
cdp_ts/utils/logger.py
cdp_ts/utils/utils.py
cdp_ts-0.1.53.dist-info/LICENSE
cdp_ts-0.1.53.dist-info/METADATA
cdp_ts-0.1.53.dist-info/WHEEL
cdp_ts-0.1.53.dist-info/top_level.txt
cdp_ts-0.1.53.dist-info/RECORD
