Metadata-Version: 2.1
Name: cdp-ts
Version: 0.1.53
Summary: A python implementation of Concatenated-Decision-Path method for time series classification
Home-page: https://github.com/naviveztim/CDP_python
Author: Ivan Mitzev
Maintainer: Ivan Mitzev
Maintainer-email: cdp_project@outlook.com
License: new BSD
Download-URL: https://github.com/naviveztim/CDP_python
Platform: UNKNOWN
Classifier: Development Status :: 3 - Alpha
Classifier: Intended Audience :: Science/Research
Classifier: Intended Audience :: Developers
Classifier: Programming Language :: Python
Classifier: Topic :: Software Development
Classifier: Topic :: Scientific/Engineering
Classifier: Operating System :: Microsoft :: Windows
Classifier: Operating System :: POSIX
Classifier: Operating System :: Unix
Classifier: Operating System :: MacOS
Classifier: Programming Language :: Python :: 3.6
Classifier: Programming Language :: Python :: 3.8
Classifier: Programming Language :: Python :: 3.9
Classifier: Programming Language :: Python :: 3.10
Classifier: Programming Language :: Python :: 3.11
License-File: LICENSE
Requires-Dist: numpy (>=1.19.5)
Requires-Dist: numba (>=0.53.1)
Requires-Dist: setuptools (>=58.0.4)
